{
    "id": "battery_voltage_changed",
    "title": {
        "en": "Battery voltage changed",
        "sv": "Batterispänningen ändrades"
    },
    "titleFormatted": {
        "en": "Battery voltage changed to [[voltage]]",
        "sv": "Batterispänningen ändrades till [[voltage]]"
    },
    "tokens": [
        {
            "name": "voltage",
            "type": "number",
            "title": {
                "en": "Voltage",
                "sv": "Spänning"
            },
            "example": {
                "en": "54.5"
            }
        }
    ],
    "args": [
        {
            "name": "device",
            "type": "device",
            "placeholder": {
                "en": "Select GX device",
                "sv": "Välj GX enhet"
            },
            "filter": "driver_id=gx"
        }
    ]
}