[
    {
        "type": "group",
        "label": {
            "en": "Network",
            "sv": "Nätverk"
        },
        "children": [
            {
                "id": "address",
                "type": "text",
                "value": "0.0.0.0",
                "label": {
                    "en": "IP Address",
                    "sv": "IP Adress"
                }
            },
            {
                "id": "port",
                "type": "number",
                "value": 502,
                "step": 1,
                "label": {
                    "en": "Port",
                    "sv": "Port"
                }
            },
            {
                "id": "refreshInterval",
                "type": "number",
                "value": 5,
                "step": 1,
                "attr": {
                    "min": 5,
                    "max": 3600
                },
                "label": {
                    "en": "Refresh interval",
                    "sv": "Uppdateringsfrekvens"
                }
            }
        ]
    },
    {
        "type": "group",
        "label": {
            "en": "Modbus TCP",
            "sv": "Modbus TCP"
        },
        "children": [
            {
                "id": "modbus_system_unitId",
                "type": "label",
                "label": {
                    "en": "com.victronenergy.system",
                    "sv": "com.victronenergy.system"
                },
                "value": "100"
            },
            {
                "id": "modbus_vebus_unitId",
                "type": "number",
                "step": 1,
                "value": -1,
                "label": {
                    "en": "com.victronenergy.vebus",
                    "sv": "com.victronenergy.vebus"
                },
                "hint": {
                    "en": "To see a list of available devices, and their Address, go to Settings -> Services -> Modbus/TCP -> Available services.",
                    "sv": "För att se listan av enheter, gå till Inställningar -> Tjänster -> Modbus/TCP -> Tillgängliga tjänster."
                }
            },
            {
                "id": "modbus_battery_unitId",
                "type": "number",
                "step": 1,
                "value": -1,
                "label": {
                    "en": "com.victronenergy.battery",
                    "sv": "com.victronenergy.battery"
                },
                "hint": {
                    "en": "To see a list of available devices, and their Address, go to Settings -> Services -> Modbus/TCP -> Available services.",
                    "sv": "För att se listan av enheter, gå till Inställningar -> Tjänster -> Modbus/TCP -> Tillgängliga tjänster."
                }
            },
            {
                "id": "modbus_grid_unitId",
                "type": "number",
                "step": 1,
                "label": {
                    "en": "com.victronenergy.grid",
                    "sv": "com.victronenergy.grid"
                },
                "hint": {
                    "en": "To see a list of available devices, and their Address, go to Settings -> Services -> Modbus/TCP -> Available services.",
                    "sv": "För att se listan av enheter, gå till Inställningar -> Tjänster -> Modbus/TCP -> Tillgängliga tjänster."
                }
            }
        ]
    },
    {
        "type": "group",
        "label": {
            "en": "SSH",
            "sv": "SSH"
        },
        "children": [
            {
                "id": "ssh_user",
                "type": "text",
                "value": "root",
                "label": {
                    "en": "User",
                    "sv": "User"
                },
                "hint": {
                    "en": "Normally the user is root unless you have made a custom setup.",
                    "sv": "Vanligen heter användaren root, om ingen speciell uppsättning gjorts."
                }
            },
            {
                "id": "ssh_private_key",
                "type": "textarea",
                "value": "",
                "label": {
                    "en": "SSH private key",
                    "sv": "SSH privat nyckel"
                },
                "hint": {
                    "en": "Paste the entire private key file content, including BEGIN and END lines",
                    "sv": "Klistra in hela innehållet från den privata nyckelfilen, inklusive BEGIN och END raderna"
                }
            }
        ]
    },
    {
        "type": "group",
        "label": {
            "en": "Charge current control",
            "sv": "Styrning av laddström"
        },
        "children": [
            {
                "id": "controlChargeCurrent",
                "type": "radio",
                "label": {
                    "en": "Control charge current",
                    "sv": "Styr laddström"
                },
                "hint": {
                    "en": "Setting this parameter to yes means that this app will start controlling the max charge current (DVCC) based on the parameters.",
                    "sv": "Sätts denna parameter till ja så kommer appen att börja styra max laddström (DVCC) baserat på parametrarna."
                },
                "value": "no",
                "values": [
                    {
                        "id": "yes",
                        "label": {
                            "en": "Yes",
                            "sv": "Ja"
                        }
                    },
                    {
                        "id": "no",
                        "label": {
                            "en": "No",
                            "sv": "Nej"
                        }
                    }
                ]
            },
            {
                "id": "chargeLevel1",
                "type": "number",
                "value": 50,
                "step": 1,
                "attr": {
                    "min": 1,
                    "max": 1000
                },
                "units": {
                    "en": "A"
                },
                "label": {
                    "en": "SoC: 0-9%"
                }
            },
            {
                "id": "chargeLevel2",
                "type": "number",
                "value": 50,
                "step": 1,
                "attr": {
                    "min": 1,
                    "max": 1000
                },
                "units": {
                    "en": "A"
                },
                "label": {
                    "en": "SoC: 10-19%"
                }
            },
            {
                "id": "chargeLevel3",
                "type": "number",
                "value": 50,
                "step": 1,
                "attr": {
                    "min": 1,
                    "max": 1000
                },
                "units": {
                    "en": "A"
                },
                "label": {
                    "en": "SoC: 20-29%"
                }
            },
            {
                "id": "chargeLevel4",
                "type": "number",
                "value": 50,
                "step": 1,
                "attr": {
                    "min": 1,
                    "max": 1000
                },
                "units": {
                    "en": "A"
                },
                "label": {
                    "en": "SoC: 30-39%"
                }
            },
            {
                "id": "chargeLevel5",
                "type": "number",
                "value": 50,
                "step": 1,
                "attr": {
                    "min": 1,
                    "max": 1000
                },
                "units": {
                    "en": "A"
                },
                "label": {
                    "en": "SoC: 40-49%"
                }
            },
            {
                "id": "chargeLevel6",
                "type": "number",
                "value": 50,
                "step": 1,
                "attr": {
                    "min": 1,
                    "max": 1000
                },
                "units": {
                    "en": "A"
                },
                "label": {
                    "en": "SoC: 50-59%"
                }
            },
            {
                "id": "chargeLevel7",
                "type": "number",
                "value": 50,
                "step": 1,
                "attr": {
                    "min": 1,
                    "max": 1000
                },
                "units": {
                    "en": "A"
                },
                "label": {
                    "en": "SoC: 60-69%"
                }
            },
            {
                "id": "chargeLevel8",
                "type": "number",
                "value": 50,
                "step": 1,
                "attr": {
                    "min": 1,
                    "max": 1000
                },
                "units": {
                    "en": "A"
                },
                "label": {
                    "en": "SoC: 70-74%"
                }
            },
            {
                "id": "chargeLevel9",
                "type": "number",
                "value": 50,
                "step": 1,
                "attr": {
                    "min": 1,
                    "max": 1000
                },
                "units": {
                    "en": "A"
                },
                "label": {
                    "en": "SoC: 75-79%"
                }
            },
            {
                "id": "chargeLevel10",
                "type": "number",
                "value": 50,
                "step": 1,
                "attr": {
                    "min": 1,
                    "max": 1000
                },
                "units": {
                    "en": "A"
                },
                "label": {
                    "en": "SoC: 80-84%"
                }
            },
            {
                "id": "chargeLevel11",
                "type": "number",
                "value": 50,
                "step": 1,
                "attr": {
                    "min": 1,
                    "max": 1000
                },
                "units": {
                    "en": "A"
                },
                "label": {
                    "en": "SoC: 85-89%"
                }
            },
            {
                "id": "chargeLevel12",
                "type": "number",
                "value": 50,
                "step": 1,
                "attr": {
                    "min": 1,
                    "max": 1000
                },
                "units": {
                    "en": "A"
                },
                "label": {
                    "en": "SoC: 90-94%"
                }
            },
            {
                "id": "chargeLevel13",
                "type": "number",
                "value": 50,
                "step": 1,
                "attr": {
                    "min": 1,
                    "max": 1000
                },
                "units": {
                    "en": "A"
                },
                "label": {
                    "en": "SoC: 95-100%"
                }
            }
        ]
    },
    {
        "type": "group",
        "label": {
            "en": "Information",
            "sv": "Information"
        },
        "children": [
            {
                "id": "vrmId",
                "type": "label",
                "label": {
                    "en": "VRM portal ID",
                    "sv": "VRM portal ID"
                },
                "value": ""
            },
            {
                "id": "essMode",
                "type": "label",
                "label": {
                    "en": "ESS Mode",
                    "sv": "ESS Mode"
                },
                "value": ""
            },
            {
                "id": "timeSinceLastFullCharge",
                "type": "label",
                "label": {
                    "en": "Time since last full charge",
                    "sv": "Tid sedan full laddning"
                },
                "value": ""
            },
            {
                "id": "minimumSOC",
                "type": "label",
                "label": {
                    "en": "Minimum SoC (unless grid fails)",
                    "sv": "Lägsta SoC (om inte elnätet är frånkopplat)"
                },
                "value": ""
            },
            {
                "id": "vebusAlarms",
                "type": "label",
                "label": {
                    "en": "VE Bus alarms",
                    "sv": "VE Bus alarm"
                },
                "value": ""
            },
            {
                "id": "vebusWarnings",
                "type": "label",
                "label": {
                    "en": "VE Bus warnings",
                    "sv": "VE Bus varningar"
                },
                "value": ""
            }
        ]
    },
    {
        "type": "group",
        "label": {
            "en": "Debug",
            "sv": "Felsökning"
        },
        "children": [
            {
                "id": "last_error",
                "type": "textarea",
                "label": {
                    "en": "Most recent API error",
                    "sv": "Senaste API felmeddelandet"
                },
                "value": ""
            }
        ]
    }
]